nlerosion/ErosioNL.py
nlerosion/__init__.py
nlerosion/advance_time.py
nlerosion/create_synth_landform.py
nlerosion/make_plot.py
nlerosion/nonlinear_function.py
nlerosion/numerical_fluxes.py
nlerosion/read_asc.py
nlerosion/relative_coeff.py
nlerosion/run_code_simple.py
nlerosion-1.0.0.dist-info/LICENSE
nlerosion-1.0.0.dist-info/METADATA
nlerosion-1.0.0.dist-info/WHEEL
nlerosion-1.0.0.dist-info/top_level.txt
nlerosion-1.0.0.dist-info/RECORD
